{"2":{"id":2,"nameId":"Salle A V"},"3":{"id":3,"nameId":"Salle A VI"},"4":{"id":4,"nameId":"Salle Finale"},"5":{"id":5,"nameId":"Salle A I"},"6":{"id":6,"nameId":"Salle A II"},"7":{"id":7,"nameId":"Salle A III"},"8":{"id":8,"nameId":"Salle A IV"},"9":{"id":9,"nameId":"Salle B V"},"10":{"id":10,"nameId":"Salle B VI"},"11":{"id":11,"nameId":"Salle B I"},"12":{"id":12,"nameId":"Salle B II"},"13":{"id":13,"nameId":"Salle B III"},"14":{"id":14,"nameId":"Salle B IV"},"15":{"id":15,"nameId":"Salle C V"},"16":{"id":16,"nameId":"Salle C VI"},"17":{"id":17,"nameId":"Salle C I"},"18":{"id":18,"nameId":"Salle C II"},"19":{"id":19,"nameId":"Salle C III"},"20":{"id":20,"nameId":"Salle C IV"}}